LICENSE
MANIFEST.in
README.md
setup.py
finite/__init__.py
finite/dfa.py
finite.egg-info/PKG-INFO
finite.egg-info/SOURCES.txt
finite.egg-info/dependency_links.txt
finite.egg-info/top_level.txt
test/test_dfa.py