Metadata-Version: 1.1
Name: finite
Version: 0.1.0
Summary: Yet another finite state automaton
Home-page: http://github.com/barnybug/finite/
Author: Barnaby Gray
Author-email: barnaby@pickle.me.uk
License: MIT
Platform: UNKNOWN
Classifier: Development Status :: 3 - Alpha
Classifier: Topic :: Software Development :: Libraries :: Python Modules
Classifier: Intended Audience :: Developers
Classifier: License :: OSI Approved :: MIT License
